{
  "posts": [
  
  {
    
    "id": 1,
    "Region": "Хліб пшеничний вищого гатунку",
    "Obl": "Мілієвський мукомольний комбінат",
    "Oil": "12.06.2001",
    "date": "магазин № 12",
    "numFuel": "200",
    "numDizFuel": "1,25",
    "numOil": "Так"
    
  },
  {
    
    "id": 2, 
    "Region": "Хліб житній",
    "Obl": "Мілієвський мукомольний комбінат",
    "Oil": "03.09.2001",
    "date": "магазин № 19",
    "numFuel": "400",
    "numDizFuel": "1,30",
    "numOil": "Так"
    
    
  },
  {
    
    "id": 3,
    "Region": "Хліб пшеничний вищого гатунку",
    "Obl": "Мілієвський мукомольний комбінат",
    "Oil": "04.05.2001",
    "date": "Кафе “Астра”",
    "numFuel": "890",
    "numDizFuel": "1,25",
    "numOil": "Ні"
    
  },
  {
        
    "id": 4,
    "Region": "Хліб житній",
    "Obl": "Одеський мукомольний комбінат",
    "Oil": "23.07.2001",
    "date": "Бар “Веста”",
    "numFuel": "420",
    "numDizFuel": "1,20",
    "numOil": "Ні"
    
  },
  {
        
    "id": 5,
    "Region": "Хліб житній з тміном",
    "Obl": "Мілієвський мукомольний комбінат",
    "Oil": "18.12.2001",
    "date": "магазин № 21",
    "numFuel": "2000",
    "numDizFuel": "1,30",
    "numOil": "Так"
    
  },
  {
        
    "id": 6,
    "Region": "Хліб житній",
    "Obl": "Одеський мукомольний комбінат",
    "Oil": "19.04.2001",
    "date": "Кафе “Астра”",
    "numFuel": "370",
    "numDizFuel": "1,20",
    "numOil": "Так"
    
  }
    
  ]
}
